repti_telemetry/__init__.py
repti_telemetry/healthcheck/__init__.py
repti_telemetry/logging/__init__.py
repti_telemetry/logging/context.py
repti_telemetry/logging/decorators.py
repti_telemetry/logging/filters.py
repti_telemetry/logging/formatter.py
repti_telemetry/logging/middleware.py
repti_telemetry/logging/setup.py
repti_telemetry/metrics/__init__.py
repti_telemetry/metrics/client.py
repti_telemetry/metrics/decorators.py
repti_telemetry/metrics/middleware.py
repti_telemetry/tracing/__init__.py
repti_telemetry-2.1.0.dist-info/METADATA
repti_telemetry-2.1.0.dist-info/WHEEL
repti_telemetry-2.1.0.dist-info/top_level.txt
repti_telemetry-2.1.0.dist-info/RECORD
