Metadata-Version: 2.4
Name: repti-telemetry
Version: 2.1.0
Summary: Unified telemetry library for ReptiDex microservices - logging, metrics, and tracing
Author-email: ReptiDex Team <dev@reptidex.com>
License: MIT
Requires-Python: >=3.12
Requires-Dist: python-json-logger>=2.0.7
Requires-Dist: pydantic>=2.5.0
Requires-Dist: pydantic-settings>=2.0.3
Provides-Extra: fastapi
Requires-Dist: fastapi>=0.104.0; extra == "fastapi"
Requires-Dist: starlette>=0.27.0; extra == "fastapi"
Provides-Extra: metrics
Requires-Dist: prometheus-client>=0.19.0; extra == "metrics"
Provides-Extra: all
Requires-Dist: fastapi>=0.104.0; extra == "all"
Requires-Dist: starlette>=0.27.0; extra == "all"
Requires-Dist: prometheus-client>=0.19.0; extra == "all"
Provides-Extra: dev
Requires-Dist: pytest>=7.4.3; extra == "dev"
Requires-Dist: pytest-asyncio>=0.21.1; extra == "dev"
Requires-Dist: pytest-cov>=4.1.0; extra == "dev"
Requires-Dist: black>=23.11.0; extra == "dev"
Requires-Dist: isort>=5.12.0; extra == "dev"
Requires-Dist: flake8>=6.1.0; extra == "dev"
Requires-Dist: mypy>=1.7.1; extra == "dev"
Requires-Dist: pre-commit>=3.5.0; extra == "dev"
Requires-Dist: bandit>=1.7.5; extra == "dev"
Requires-Dist: build>=1.0.0; extra == "dev"
Requires-Dist: twine>=4.0.0; extra == "dev"
